{"ewram": {"gClipdataCollisionTypes": 33562624, "gClipdataCollisionTypes_Tilemap": 33563648, "gClipdataBehaviorTypes": 33566720, "gClipdataBehaviorTypes_Tilemap": 33568768, "gTilemap": 33570816, "gCommonTilemap": 33579008, "gDecompBg3Map": 33583104, "gHazeValues": 33710848, "gPreviousHazeValues": 33713408, "gCurrentCharacterGfx": 33715968, "gMakeSolidBlocks": 33716096, "gDecompClipdataMap": 33716224, "gDecompBg0Map": 33728512, "gDecompBg1Map": 33740800, "gDecompBg2Map": 33753088, "gMinimapTilesWithObtainedItems": 33765376, "gDecompressedMinimapVisitedTiles": 33767424, "gDecompressedMinimapData": 33769472, "unk_02035400": 33772544, "gNeverReformBlocks": 33774592, "gItemsCollected": 33778688, "gVisitedMinimapTiles": 33780736, "gEventsTriggered": 33783296, "gMinimapTilesGfx": 33783328, "gSram": 33783808, "gSramDemoInputData": 33812608, "gSramDemoInputDuration": 33813120}, "iwram": {"gDebugFlag": 50331648, "gSramErrorFlag": 50331649, "gFrameCounter16Bit": 50331650, "gStereoFlag": 50331652, "gSubGameModeStage": 50331653, "gWrittenToBLDALPHA": 50331654, "gWrittenToBLDCNT_Internal": 50331656, "gWrittenToDISPCNT": 50331658, "gWrittenToWININ_H": 50331662, "gWrittenToWINOUT_L": 50331663, "gBackdropColor": 50331664, "gWrittenToBLDY": 50331666, "gFileScreenOptionsUnlocked": 50331668, "gLanguage": 50331680, "gGameCompletion": 50331684, "gCompletedGameFlagCopy": 50331688, "gMonochromeBgFading": 50331689, "gWhichBGPositionIsWrittenToBG3OFS": 50331690, "gSamusOnTopOfBackgrounds": 50331691, "gDifficulty": 50331692, "gUseMotherShipDoors": 50331693, "gTimeAttackFlag": 50331694, "gCutsceneToSkip": 50331695, "gMusicTrackInfo": 50331696, "gCurrentDemo": 50331704, "gResetGame": 50331708, "gDisableScrolling": 50331709, "gSlowScrollingTimer": 50331710, "gSkipDoorTransition": 50331714, "gDisableSoftreset": 50331715, "gCollectingTank": 50331716, "gDisableAnimatedGraphicsTimer": 50331717, "gAnimatedGraphicsToUpdate": 50331718, "gDisableDoorAndTanks": 50331720, "gDisablePause": 50331721, "gHideHud": 50331722, "gShipLandingFlag": 50331723, "gDisableClipdataChangingTransparency": 50331724, "gDisableAnimatedPalette": 50331725, "gInGameCutscenesTriggered": 50331728, "gCurrentArea": 50331732, "gCurrentRoom": 50331733, "gLastDoorUsed": 50331734, "gLastDoorProperties": 50331735, "gDisplayLocationText": 50331736, "gMinimapX": 50331737, "gMinimapY": 50331738, "gNumberOfNeverReformBlocks": 50331739, "gNumberOfItemsCollected": 50331747, "gCurrentHazeValue": 50331755, "gEffectYPosition": 50331756, "gEffectYPositionOffset": 50331758, "gScreenShakeXOffset": 50331761, "gScreenShakeYOffset": 50331762, "gScreenShakeRelated": 50331764, "gDISPCNTBackup": 50331766, "gSpriteset": 50331768, "gCurrentClipdataAffectingAction": 50331769, "gSpritesetEntryUsed": 50331770, "gDoorUnlockTimer": 50331771, "gDisableDrawingSprites": 50331772, "gCurrentCutscene": 50331773, "gTourianEscapeCutsceneStage": 50331774, "gFreeMovementLockCamera": 50331775, "gHazeInfo": 50331776, "gIoRegistersBackup": 50331784, "gBgPointersAndDimensions": 50331804, "gCurrentRoomEntry": 50331836, "gCurrentAffectingClipdata": 50331868, "gBackgroundPositions": 50331876, "gWaitingSpacePiratesPosition": 50331896, "gBg2Movement": 50331900, "gLockScreen": 50331904, "gSuitFlashEffect": 50331912, "gScreenShakeY": 50331920, "gScreenShakeX": 50331924, "gCurrentScrolls": 50331928, "gCurrentPowerBomb": 50331952, "gCamera": 50331972, "gMaxInGameTimerFlag": 50331980, "gInGameTimer": 50331984, "gBestCompletionTimes": 50331988, "gInGameTimerAtBosses": 50332036, "gLastElevatorUsed": 50332056, "gInGameCutscene": 50332060, "gAlarmTimer": 50332072, "gSpriteData": 50332076, "gSpritesetSpritesID": 50333420, "gSpritesetGfxSlots": 50333435, "gSubSpriteData1": 50333452, "gSubSpriteData2": 50333472, "gParasiteRelated": 50333492, "gCurrentSprite": 50333496, "gSpriteDebris": 50333552, "gPreviousVerticalCollisionCheck": 50333680, "gPreviousCollisionCheck": 50333681, "gIgnoreSamusAndSpriteCollision": 50333682, "gSpriteDrawOrder": 50333683, "gBossWork": 50333708, "gSpriteRng": 50333756, "gParticleEffects": 50333760, "gMissileHighlightStatus": 50333952, "gPowerBombHighlightStatus": 50333953, "gSuperMissileHighlightStatus": 50333954, "gUpdateMinimapFlag": 50333955, "gEnergyDigits": 50333956, "gMaxEnergyDigits": 50333960, "gMissileDigits": 50333964, "gPowerBombDigits": 50333968, "gSuperMissileDigits": 50333972, "gCurrentParticleEffectOamFramePointer": 50333976, "gAmmoDigitsGfx": 50333980, "gCurrentEscapeStatus": 50334044, "gEscapeTimerCounter": 50334045, "gEscapeTimerDigits": 50334046, "gParticleEscapeOamFrames": 50334052, "gEnergyRefillAnimation": 50334102, "gMissileRefillAnimation": 50334103, "gSuperMissileRefillAnimation": 50334104, "gPowerBombRefillAnimation": 50334105, "gParticleSamusReflectionOamFrames": 50334106, "gProjectileData": 50334252, "gArmCannonY": 50334700, "gArmCannonX": 50334702, "gPauseScreenFlag": 50334704, "gAreaBeforeTransition": 50334705, "gCurrentItemBeingAcquired": 50334706, "gOptionsOptionSelected": 50334707, "gBg0HOFS_NonGameplay": 50334708, "gBg0VOFS_NonGameplay": 50334710, "gBg1HOFS_NonGameplay": 50334712, "gBg1VOFS_NonGameplay": 50334714, "gBg2HOFS_NonGameplay": 50334716, "gBg2VOFS_NonGameplay": 50334718, "gBg3HOFS_NonGameplay": 50334720, "gBg3VOFS_NonGameplay": 50334722, "gCurrentOamRotation": 50334724, "gCurrentOamScaling": 50334726, "gLastAreaNameVisited": 50334728, "gCurrentMessage": 50334732, "gSramCorruptFlag": 50334748, "gIsLoadingFile": 50334749, "gMostRecentSaveFile": 50334750, "gHasSaved": 50334751, "gUnk_3000c20": 50334752, "gSramOperationStage": 50334753, "gSaveFilesInfo": 50334756, "gStartingInfo": 50334828, "gMainGameMode": 50334832, "gGameModeSub1": 50334834, "gGameModeSub2": 50334836, "gGameModeSub3": 50334837, "gVblankActive": 50334838, "gFrameCounter8Bit": 50334839, "gVBlankRequestFlag": 50334840, "gInterruptCode": 50334844, "gOamData": 50335356, "gButtonInput": 50336636, "gPreviousButtonInput": 50336638, "gChangedInput": 50336640, "gNextOamSlot": 50336642, "gWrittenToBG2X": 50336660, "gWrittenToBG2Y": 50336664, "gWrittenToMOSAIC_H": 50336668, "gWrittenToMOSAIC_L": 50336670, "gBg2Scaling": 50336672, "gUnk_30013a2": 50336674, "gBg2Rotation": 50336676, "gWrittenToBG2PA": 50336678, "gWrittenToBG2PB": 50336680, "gWrittenToBG2PC": 50336682, "gWrittenToBG2PD": 50336684, "gWrittenToBLDY_NonGameplay": 50336686, "gWrittenToBLDALPHA_L": 50336688, "gWrittenToBLDALPHA_H": 50336690, "gBg0XPosition": 50336692, "gBg0YPosition": 50336694, "gBg1XPosition": 50336696, "gBg1YPosition": 50336698, "gBg2XPosition": 50336700, "gBg2YPosition": 50336702, "gBg3XPosition": 50336704, "gBg3YPosition": 50336706, "gDemoState": 50336722, "gSamusData": 50336724, "gSamusDataCopy": 50336756, "gSamusWeaponInfo": 50336788, "gSamusEcho": 50336796, "gScrewSpeedAnimation": 50337064, "gEquipment": 50337072, "gSamusHazardDamage": 50337092, "gSamusEnvironmentalEffects": 50337100, "gSamusPhysics": 50337160, "gPreviousXPosition": 50337280, "gPreviousYPosition": 50337282, "gEndingFlags": 50337284, "gPreventMovementTimer": 50337286, "gDisableDrawingSamusAndScrolling": 50337288, "gTimeAttackData": 50337292, "gButtonAssignments": 50337420, "gTimeAttackRecord": 50337428, "gNonGameplayRAM": 50337476, "gVBlankCallback": 50339052, "gHBlankCallback": 50339056, "gVCountCallback": 50339060, "gSerialCommunicationCallback": 50339064, "gTimer3Callback": 50339068, "gMusicInfo": 50339072, "gUnk_300376c": 50345836, "gPsgSounds": 50345876, "gSoundChannelBackup": 50346036, "gSoundChannelTrack2Backup": 50346428, "gSoundQueue": 50346820, "gSoundCodeAPointer": 50346892, "gSoundCodeA": 50346896, "gSoundCodeBPointer": 50348520, "gSoundCodeB": 50348524, "gSoundCodeCPointer": 50348688, "gSoundCodeC": 50348692, "gTrack0Variables": 50348872, "gTrack1Variables": 50349832, "gTrack2Variables": 50350632, "gTrack3Variables": 50350792, "gTrack4Variables": 50350952, "gTrack5Variables": 50351112, "gTrack6Variables": 50351272, "gTrack7Variables": 50351512, "gTrack8Variables": 50351592, "gUnk_03004fc9": 50352073, "gDemoInputData": 50352074, "gDemoInputDuration": 50352586, "gDemoInputNumber": 50353098, "gDemoInputTimer": 50353100, "gDemoInput": 50353102, "gNotPressingUp": 50353104, "gSamusPalette": 50353120, "gSamusPaletteSize": 50353216, "gWrittenToWIN1H": 50353224, "gWrittenToWIN1V": 50353226, "gWrittenToBLDCNT": 50353228, "gTilemapAndClipPointers": 50353232, "gHatchData": 50353244, "gNumberOfValidHatchesInRoom": 50353372, "gDoorPositionStart": 50353376, "gHatchesState": 50353380, "gBg3Movement": 50353388, "gBg0Movement": 50353396, "gTilesetTransparentColor": 50353404, "gUnusedStruct_3005504": 50353412, "gSamusDoorPositionOffset": 50353420, "gDestinationRoom": 50353422, "gBg3CntDuringDoorTransition": 50353424, "gBg1CntDuringDoorTransition": 50353426, "gUnk_3005514": 50353428, "gScreenYOffset": 50353429, "gScreenXOffset": 50353430, "gRainSoundEffect": 50353432, "gWaterMovement": 50353436, "gColorFading": 50353440, "gBrokenBlocks": 50353448, "gLastTankCollected": 50353832, "gBombChains": 50353836, "gActiveBombChainTypes": 50353852, "gTransparencyRelated": 50353856, "gDefaultTransparency": 50353860, "gBldalphaData1": 50353868, "gBldalphaData2": 50353876, "gBLDYData1": 50353884, "gBLDYData2": 50353892, "gAnimatedPaletteTiming": 50353900, "gHatchFlashingAnimation": 50353904, "gAnimatedGraphicsEntry": 50353908, "gBackgroundEffect": 50353912, "gScrollCounter": 50353920, "gClipdataCodePointer": 50353924, "gCurrentRoomScrollDataPointer": 50353928, "gScrollingVelocityCaps": 50353940, "gHazeLoops": 50353948, "gUnk_3005728": 50353960, "gUnk_3005729": 50353961, "gHazeProcessCodePointer": 50353964, "gAnimatedGraphicsData": 50353968, "gTankAnimations": 50354160, "gMaintainedInputData": 50354176, "gUnk_3005804": 50354180, "gOamXOffset_NonGameplay": 50354182, "gOamYOffset_NonGameplay": 50354183, "gIoTransferInfo": 50354184, "gMultiBootParamData": 50354208, "gDataSentPointer": 50354284, "gDataSentSize": 50354288, "gUnk_3005874": 50354292, "gUnk_3005880": 50354304, "gUnk_3005884": 50354308, "gUnk_3005888": 50354312, "gCableLinkSerialTransferInfo": 50354320, "gSerialTransferUpdateResult": 50354344, "gUnk_30058aa": 50354346, "gSerialTransferDataTimer": 50354348, "gSerialTransferStartupTimer": 50354350, "gUnk_30058af": 50354351, "gSerialTransferGbaDetectedCount": 50354352, "gSerialTransferGbaId": 50354353, "gRegIme_Backup": 50354354, "gRegIe_Backup": 50354356, "gRegTm3Cnt_H_Backup": 50354358, "gRegSiocnt_Backup": 50354360, "gRegRcnt_Backup": 50354362, "gErrorFlag": 50354364, "gUnk_30058c0": 50354368, "gUnk_30058c4": 50354372, "gUnk_30058cc": 50354380, "gUnk_30058cd": 50354381, "gUnk_30058ce": 50354382, "gUnk_30058cf": 50354383, "gUnk_30058d0": 50354384, "gUnk_30058d2": 50354386, "gUnk_30058d3": 50354387, "gUnk_30058d5": 50354389, "gUnk_30058d6": 50354390, "gUnk_30058d8": 50354392, "gUnk_30058da": 50354394, "gTrackData8": 50354448, "gTrackData3": 50354512, "gTrackData1": 50354576, "gTrackData6": 50354640, "gTrackData4": 50354704, "gTrackData0": 50354768, "gTrackData7": 50354832, "gTrackData2": 50354896, "gTrackData5": 50354960, "gUnk_3005b50": 50355024, "gUnk_3005b54": 50355028, "gCableLinkInfo": 50355040, "gRandoEquipment": 50355460, "gRandoLocationBitfields": 50355464, "gIncomingItem": 50355492, "gIncomingMessage": 50355496, "gReceivingFromMultiworld": 50355504, "gIgnoreLocalItems": 50355505, "gMultiworldItemCount": 50355506, "gCurrentRandoMessage": 50355508, "gDynamicMessageBuffer": 50355516, "sp_sys": 50364000, "sp_irq": 50364320, "gInterruptCheckFlag": 50364408, "gIntrCodePointer": 50364412, "intr_vector": 50364412}, "rom": {"sMorphBallGfx": 137050368, "sMorphBallPal": 137051040, "sMorphBallOam_Idle_Frame0": 137051072, "sMorphBallOam_Idle_Frame1": 137051080, "sMorphBallOam_Idle_Frame2": 137051088, "sMorphBallOutsideOam_Idle_Frame0": 137051096, "sMorphBallOutsideOam_Idle_Frame1": 137051104, "sMorphBallOutsideOam_Idle_Frame2": 137051112, "sMorphBallOutsideOam_Idle_Frame3": 137051120, "sMorphBallOutsideOam_Idle_Frame4": 137051128, "sMorphBallOam_Idle": 137051136, "sMorphBallOutsideOam_Idle": 137051176, "sPowerGripGfx": 137051224, "sPowerGripPal": 137052340, "sPowerGripOAM_Idle_Frame0": 137052404, "sPowerGripOAM_Idle_Frame1": 137052412, "sPowerGripOAM_Idle_Frame2": 137052420, "sPowerGripGlowOAM_Idle_Frame0": 137052428, "sPowerGripGlowOAM_Idle_Frame2": 137052448, "sPowerGripGlowOAM_Idle_Frame4": 137052468, "sPowerGripGlowOAM_Idle_Frame6": 137052488, "sPowerGripGlowOAM_Idle_Frame1": 137052508, "sPowerGripOAM_Idle": 137052516, "sPowerGripGlowOAM_Idle": 137052556, "sChargeBeamIdleYMovement": 137052676, "sChargeBeamGfx": 137052808, "sChargeBeamPal": 137053780, "sChargeBeamOam_Visible": 137054544, "sChargeBeamOam_Spawning": 137054584, "sChargeBeamGlowOam_Idle": 137054688, "sChozoStatueMultiSpriteData_Standing": 137055140, "sChozoStatueMultiSpriteData_Sitting": 137055156, "sChozoStatueMultiSpriteData_Seated": 137055244, "sChozoStatueFlashingPaletteRows": 137055260, "sChozoStatueLongBeamGfx": 137055264, "sChozoStatueLongBeamPal": 137060604, "sChozoStatuePartOam_LegStanding": 137062280, "sChozoStatuePartOam_LegSitting": 137062296, "sChozoStatuePartOam_LegSeated": 137062376, "sChozoStatueOam_Idle": 137062392, "sChozoStatuePartOam_EyeOpened": 137062408, "sChozoStatuePartOam_EyeClosing": 137062424, "sChozoStatuePartOam_EyeOpening": 137062448, "sChozoStatuePartOam_EyeClosed": 137062472, "sChozoStatuePartOam_ArmIdle": 137062488, "sChozoStatuePartOam_ArmGlow": 137062504, "sChozoStatuePartOam_ArmSamusGrabbed": 137062576, "sChozoBallOam_NormalClosed": 137062592, "sChozoBallOam_NormalRevealing": 137062632, "sChozoBallOam_NormalRevealed": 137062664, "sChozoStatueRefillOam": 137062704, "sChozoStatuePartOam_GlowIdle": 137063032, "sChozoStatueIceBeamGfx": 137063360, "sChozoStatueIceBeamPal": 137068700, "sChozoStatueWaveBeamGfx": 137068860, "sChozoStatueWaveBeamPal": 137074200, "sChozoStatueBombsGfx": 137074360, "sChozoStatueBombsPal": 137079716, "sChozoStatueSpeedboosterGfx": 137079876, "sChozoStatueSpeedboosterPal": 137085244, "sChozoStatueHighJumpGfx": 137085404, "sChozoStatueHighJumpPal": 137090892, "sChozoStatueScrewAttackGfx": 137091052, "sChozoStatueScrewAttackPal": 137096564, "sChozoStatueVariaGfx": 137096724, "sChozoStatueVariaPal": 137102116, "sUnknownItemChozoStatueMultiSpriteData_Standing": 137102608, "sUnknownItemChozoStatueMultiSpriteData_Sitting": 137102624, "sUnknownItemChozoStatueMultiSpriteData_Seated": 137102712, "sUnknownItemChozoStatueFlashingPaletteRows": 137102728, "sChozoStatueSpaceJumpGfx": 137102732, "sChozoStatueSpaceJumpPal": 137108144, "sUnknownItemChozoStatuePartOam_LegStanding": 137110032, "sUnknownItemChozoStatuePartOam_LegSitting": 137110048, "sUnknownItemChozoStatuePartOam_LegSeated": 137110128, "sUnknownItemChozoStatueOam_Idle": 137110144, "sUnknownItemChozoStatuePartOam_EyeOpened": 137110160, "sUnknownItemChozoStatuePartOam_EyeClosing": 137110176, "sUnknownItemChozoStatuePartOam_EyeOpening": 137110200, "sUnknownItemChozoStatuePartOam_EyeClosed": 137110224, "sUnknownItemChozoStatuePartOam_ArmIdle": 137110240, "sUnknownItemChozoStatuePartOam_ArmGlow": 137110256, "sUnknownItemChozoStatuePartOam_ArmSamusGrabbed": 137110328, "sChozoBallOam_UnknownClosed": 137110344, "sChozoBallOam_UnknownRevealing": 137110384, "sChozoBallOam_UnknownRevealed": 137110416, "sUnknownItemChozoStatueRefillOam": 137110456, "sUnknownItemChozoStatuePartOam_GlowIdle": 137110784, "sChozoStatueGravitySuitGfx": 137111112, "sChozoStatueGravitySuitPal": 137116540, "sChozoStatuePlasmaBeamGfx": 137116700, "sChozoStatuePlasmaBeamPal": 137122124, "sHatchTypeTable": 137761160, "sHatchLockEventsBrinstar": 137761168, "sHatchLockEventsKraid": 137761176, "sHatchLockEventsCrateria": 137761184, "sHatchLockEventsChozodia": 137761216, "sEventBasedConnections": 137761344, "sAreaConnections": 137761508, "sHatchesAnimationDurationCounter": 137761586, "sHatchesTilemapValues": 137761592, "sNumberOfHatchLockEventsPerArea": 137761608, "sMinimapTilesGfx": 138473780, "sPauseScreen_40f4c4": 138478900, "sMapScreenAreaNamesGfx": 138486068, "sMinimapTilesPal": 138486736, "sCharactersGfx": 138503376, "sJapaneseText_Message_Dummy": 138683600, "sJapaneseText_Message_EnergyTankAcquired": 138683614, "sJapaneseText_Message_MissileTankAcquired": 138683688, "sJapaneseText_Message_FirstMissileTank": 138683776, "sJapaneseText_Message_SuperMissileTankAcquired": 138683826, "sJapaneseText_Message_FirstSuperMissileTank": 138683942, "sJapaneseText_Message_PowerBombTankAqcuired": 138684012, "sJapaneseText_Message_FirstPowerBombTank": 138684110, "sJapaneseText_Message_LongBeam": 138684168, "sJapaneseText_Message_ChargeBeam": 138684210, "sJapaneseText_Message_IceBeam": 138684258, "sJapaneseText_Message_WaveBeam": 138684298, "sJapaneseText_Message_UnknownItemPlasma": 138684342, "sJapaneseText_Message_Bomb": 138684364, "sJapaneseText_Message_VariaSuit": 138684388, "sJapaneseText_Message_UnknownItemGravity": 138684432, "sJapaneseText_Message_MorphBall": 138684454, "sJapaneseText_Message_SpeedBooster": 138684498, "sJapaneseText_Message_HighJump": 138684554, "sJapaneseText_Message_ScrewAttack": 138684592, "sJapaneseText_Message_UnknownItemSpaceJump": 138684646, "sJapaneseText_Message_PowerGrip": 138684668, "sJapaneseText_Message_SavePrompt": 138684714, "sJapaneseText_Message_SaveComplete": 138684752, "sJapaneseText_Message_WeaponRessuplyComplete": 138684770, "sJapaneseText_Message_EnergyTankRechargeComplete": 138684794, "sJapaneseText_Message_WeaponsAndEnergyRestored": 138684818, "sJapaneseText_Message_BrinstarMap": 138684854, "sJapaneseText_Message_KraidMap": 138684910, "sJapaneseText_Message_NorfairMap": 138684960, "sJapaneseText_Message_RidleyMap": 138685014, "sJapaneseText_Message_MotherShipMap": 138685066, "sJapaneseText_Message_FullyPoweredSuit": 138685118, "sJapaneseText_Message_ZebesEscape": 138685160, "sJapaneseText_Message_ChozodiaEscape": 138685192, "sJapaneseText_Message_EnemyLocationAbnormal": 138685224, "sJapaneseText_Message_ActivateEasySleep": 138685292, "sJapaneseText_Message_PressSelectLAndR": 138685354, "sJapaneseText_Message_EasySleepPrompt": 138685408, "sJapaneseText_Location_Brinstar": 138685426, "sJapaneseText_Location_Kraid": 138685468, "sJapaneseText_Location_Norfair": 138685502, "sJapaneseText_Location_Ridley": 138685542, "sJapaneseText_Location_Tourian": 138685578, "sJapaneseText_Location_Crateria": 138685618, "sJapaneseText_Location_Chozodia": 138685660, "sJapaneseText_Location_Mothership": 138685706, "sJapaneseText_Location_PlanetZebes": 138685742, "sJapaneseText_Location_SaveRoom": 138685758, "sJapaneseText_Location_ResearchRoom": 138685774, "sJapaneseText_Location_MapRoom": 138685794, "sJapaneseText_Location_ChozoRuins": 138685810, "sJapaneseText_Location_Starship": 138685822, "sJapaneseText_Location_Unused7": 138685838, "sJapaneseText_Location_Unused8": 138685848, "sJapaneseText_Location_Unused9": 138685858, "sJapaneseText_Location_Unused10": 138685868, "sJapaneseText_Location_Unused11": 138685880, "sJapaneseText_Location_Unused12": 138685892, "sJapaneseText_Location_Unused13": 138685904, "sJapaneseText_Location_Unused14": 138685916, "sJapaneseText_Location_Unused15": 138685928, "sJapaneseText_Location_Unused16": 138685940, "sJapaneseText_Location_Unused17": 138685952, "sJapaneseText_Location_Unused18": 138685964, "sHiraganaText_Message_Dummy": 138685976, "sHiraganaText_Message_EnergyTankAcquired": 138685990, "sHiraganaText_Message_MissileTankAcquired": 138686054, "sHiraganaText_Message_FirstMissileTank": 138686128, "sHiraganaText_Message_SuperMissileTankAcquired": 138686152, "sHiraganaText_Message_FirstSuperMissileTank": 138686242, "sHiraganaText_Message_PowerBombTankAqcuired": 138686274, "sHiraganaText_Message_FirstPowerBombTank": 138686352, "sHiraganaText_Message_LongBeam": 138686378, "sHiraganaText_Message_ChargeBeam": 138686400, "sHiraganaText_Message_IceBeam": 138686424, "sHiraganaText_Message_WaveBeam": 138686446, "sHiraganaText_Message_UnknownItemPlasma": 138686470, "sHiraganaText_Message_Bomb": 138686508, "sHiraganaText_Message_VariaSuit": 138686522, "sHiraganaText_Message_UnknownItemGravity": 138686544, "sHiraganaText_Message_MorphBall": 138686582, "sHiraganaText_Message_SpeedBooster": 138686604, "sHiraganaText_Message_HighJump": 138686632, "sHiraganaText_Message_ScrewAttack": 138686654, "sHiraganaText_Message_UnknownItemSpaceJump": 138686682, "sHiraganaText_Message_PowerGrip": 138686720, "sHiraganaText_Message_SavePrompt": 138686744, "sHiraganaText_Message_SaveComplete": 138686782, "sHiraganaText_Message_WeaponRessuplyComplete": 138686804, "sHiraganaText_Message_EnergyTankRechargeComplete": 138686846, "sHiraganaText_Message_WeaponsAndEnergyRestored": 138686894, "sHiraganaText_Message_BrinstarMap": 138686950, "sHiraganaText_Message_KraidMap": 138687004, "sHiraganaText_Message_NorfairMap": 138687056, "sHiraganaText_Message_RidleyMap": 138687110, "sHiraganaText_Message_MotherShipMap": 138687162, "sHiraganaText_Message_FullyPoweredSuit": 138687222, "sHiraganaText_Message_ZebesEscape": 138687272, "sHiraganaText_Message_ChozodiaEscape": 138687318, "sHiraganaText_Message_EnemyLocationAbnormal": 138687364, "sHiraganaText_Message_ActivateEasySleep": 138687442, "sHiraganaText_Message_PressSelectLAndR": 138687510, "sHiraganaText_Message_EasySleepPrompt": 138687566, "sHiraganaText_Location_Brinstar": 138687584, "sHiraganaText_Location_Kraid": 138687598, "sHiraganaText_Location_Norfair": 138687610, "sHiraganaText_Location_Ridley": 138687624, "sHiraganaText_Location_Tourian": 138687636, "sHiraganaText_Location_Crateria": 138687650, "sHiraganaText_Location_Chozodia": 138687664, "sHiraganaText_Location_Mothership": 138687682, "sHiraganaText_Location_PlanetZebes": 138687706, "sHiraganaText_Location_SaveRoom": 138687726, "sHiraganaText_Location_ResearchRoom": 138687742, "sHiraganaText_Location_MapRoom": 138687762, "sHiraganaText_Location_ChozoRuins": 138687778, "sHiraganaText_Location_Starship": 138687798, "sHiraganaText_Location_Unused7": 138687814, "sHiraganaText_Location_Unused8": 138687824, "sHiraganaText_Location_Unused9": 138687834, "sHiraganaText_Location_Unused10": 138687844, "sHiraganaText_Location_Unused11": 138687856, "sHiraganaText_Location_Unused12": 138687868, "sHiraganaText_Location_Unused13": 138687880, "sHiraganaText_Location_Unused14": 138687892, "sHiraganaText_Location_Unused15": 138687904, "sHiraganaText_Location_Unused16": 138687916, "sHiraganaText_Location_Unused17": 138687928, "sHiraganaText_Location_Unused18": 138687940, "sEnglishText_Message_Dummy": 138687952, "sEnglishText_Message_EnergyTankAcquired": 138688014, "sEnglishText_Message_MissileTankAcquired": 138688120, "sEnglishText_Message_FirstMissileTank": 138688230, "sEnglishText_Message_SuperMissileTankAcquired": 138688264, "sEnglishText_Message_FirstSuperMissileTank": 138688398, "sEnglishText_Message_PowerBombTankAqcuired": 138688444, "sEnglishText_Message_FirstPowerBombTank": 138688546, "sEnglishText_Message_LongBeam": 138688586, "sEnglishText_Message_ChargeBeam": 138688614, "sEnglishText_Message_IceBeam": 138688646, "sEnglishText_Message_WaveBeam": 138688672, "sEnglishText_Message_UnknownItemPlasma": 138688700, "sEnglishText_Message_Bomb": 138688734, "sEnglishText_Message_VariaSuit": 138688752, "sEnglishText_Message_UnknownItemGravity": 138688782, "sEnglishText_Message_MorphBall": 138688816, "sEnglishText_Message_SpeedBooster": 138688846, "sEnglishText_Message_HighJump": 138688882, "sEnglishText_Message_ScrewAttack": 138688906, "sEnglishText_Message_UnknownItemSpaceJump": 138688940, "sEnglishText_Message_PowerGrip": 138688974, "sEnglishText_Message_SavePrompt": 138689004, "sEnglishText_Message_SaveComplete": 138689036, "sEnglishText_Message_WeaponRessuplyComplete": 138689070, "sEnglishText_Message_EnergyTankRechargeComplete": 138689142, "sEnglishText_Message_WeaponsAndEnergyRestored": 138689208, "sEnglishText_Message_BrinstarMap": 138689282, "sEnglishText_Message_KraidMap": 138689352, "sEnglishText_Message_NorfairMap": 138689416, "sEnglishText_Message_RidleyMap": 138689484, "sEnglishText_Message_MotherShipMap": 138689550, "sEnglishText_Message_FullyPoweredSuit": 138689626, "sEnglishText_Message_ZebesEscape": 138689702, "sEnglishText_Message_ChozodiaEscape": 138689820, "sEnglishText_Message_EnemyLocationAbnormal": 138689938, "sEnglishText_Message_ActivateEasySleep": 138690052, "sEnglishText_Message_PressSelectLAndR": 138690138, "sEnglishText_Message_EasySleepPrompt": 138690214, "sEnglishText_Location_Brinstar": 138690232, "sEnglishText_Location_Kraid": 138690252, "sEnglishText_Location_Norfair": 138690266, "sEnglishText_Location_Ridley": 138690284, "sEnglishText_Location_Tourian": 138690300, "sEnglishText_Location_Crateria": 138690318, "sEnglishText_Location_Chozodia": 138690338, "sEnglishText_Location_Mothership": 138690358, "sEnglishText_Location_PlanetZebes": 138690410, "sEnglishText_Location_SaveRoom": 138690438, "sEnglishText_Location_ResearchRoom": 138690460, "sEnglishText_Location_MapRoom": 138690490, "sEnglishText_Location_ChozoRuins": 138690510, "sEnglishText_Location_Starship": 138690536, "sEnglishText_Location_Unused7": 138690556, "sEnglishText_Location_Unused8": 138690584, "sEnglishText_Location_Unused9": 138690612, "sEnglishText_Location_Unused10": 138690640, "sEnglishText_Location_Unused11": 138690670, "sEnglishText_Location_Unused12": 138690700, "sEnglishText_Location_Unused13": 138690730, "sEnglishText_Location_Unused14": 138690760, "sEnglishText_Location_Unused15": 138690790, "sEnglishText_Location_Unused16": 138690820, "sEnglishText_Location_Unused17": 138690850, "sEnglishText_Location_Unused18": 138690880, "sJapaneseText_Description_LongBeam": 138690912, "sJapaneseText_Description_ChargeBeam": 138690980, "sJapaneseText_Description_IceBeam": 138691082, "sJapaneseText_Description_WaveBeam": 138691148, "sJapaneseText_Description_PlasmaBeam": 138691184, "sJapaneseText_Description_Missiles": 138691206, "sJapaneseText_Description_SuperMissiles": 138691262, "sJapaneseText_Description_Bombs": 138691348, "sJapaneseText_Description_PowerBombs": 138691380, "sJapaneseText_Description_VariaSuit": 138691450, "sJapaneseText_Description_GravitySuit": 138691536, "sJapaneseText_Description_MorphBall": 138691624, "sJapaneseText_Description_PowerGrip": 138691686, "sJapaneseText_Description_Speedbooster": 138691728, "sJapaneseText_Description_HighJump": 138691844, "sJapaneseText_Description_ScrewAttack": 138691912, "sJapaneseText_Description_SpaceJump": 138691964, "sJapaneseText_Description_UnknownItem": 138692038, "sJapaneseText_Description_Pistol": 138692074, "sJapaneseText_Story_PlanetZebes": 138692148, "sJapaneseText_Story_TheTiming": 138692426, "sJapaneseText_Story_CouldISurvive": 138692760, "sJapaneseText_Story_Emergency": 138692800, "sJapaneseText_Story_Exterminate": 138692812, "sJapaneseText_Story_Defeat": 138692872, "sJapaneseText_FileScreen_StartGame": 138692916, "sJapaneseText_FileScreen_CopySourceChoose": 138692956, "sJapaneseText_FileScreen_CopyDestinationChoose": 138692994, "sJapaneseText_FileScreen_CopyConfirm": 138693048, "sJapaneseText_FileScreen_EraseChoose": 138693128, "sJapaneseText_FileScreen_EraseConfirm": 138693156, "sJapaneseText_FileScreen_FileACorruptRevert": 138693226, "sJapaneseText_FileScreen_FileBCorruptRevert": 138693294, "sJapaneseText_FileScreen_FileCCorruptRevert": 138693362, "sJapaneseText_FileScreen_FileACorruptErase": 138693430, "sJapaneseText_FileScreen_FileBCorruptErase": 138693496, "sJapaneseText_FileScreen_FileCCorruptErase": 138693562, "sJapaneseText_FileScreen_EraseAllReformat": 138693628, "sJapaneseText_FileScreen_EraseAll": 138693694, "sJapaneseText_FileScreen_ContinueNew": 138693756, "sJapaneseText_FileScreen_ContinueNewTimeAttack": 138693780, "sJapaneseText_FileScreen_MessageOption": 138693838, "sJapaneseText_FileScreen_Difficulty": 138693910, "sJapaneseText_FileScreen_DifficultyHard": 138693982, "sJapaneseText_FileScreen_EraseFileConfirm": 138694086, "sJapaneseText_FileScreen_LinkingPleaseWait": 138694204, "sJapaneseText_FileScreen_UnableToDetectFusion": 138694252, "sJapaneseText_FileScreen_LinkingError": 138694318, "sJapaneseText_FileScreen_TurnOffConfirmLink": 138694340, "sJapaneseText_FileScreen_DoNotTurnPowerOff": 138694452, "sJapaneseText_FileScreen_DataUploadComplete": 138694486, "sJapaneseText_FileScreen_LinkComplete": 138694524, "sJapaneseText_FileScreen_BestTime": 138694576, "sJapaneseText_FileScreen_BestTime100": 138694592, "sJapaneseText_FileScreen_IdPassword": 138694616, "sJapaneseText_FileScreen_CantCopyTimeAttack": 138694634, "sJapaneseText_FileScreen_LinkingErrorTryAgain": 138694686, "sJapaneseText_FileScreen_LinkingErrorCheckConnection": 138694730, "sJapaneseText_FileScreen_GalleryUnlock": 138694832, "sJapaneseText_FileScreen_TimeAttackRecordUnlock": 138694914, "sJapaneseText_FileScreen_SoundTestUnlock": 138695008, "sJapaneseText_FileScreen_NesMetroidUnlock": 138695094, "sHiraganaText_Description_LongBeam": 138695188, "sHiraganaText_Description_ChargeBeam": 138695258, "sHiraganaText_Description_IceBeam": 138695368, "sHiraganaText_Description_WaveBeam": 138695444, "sHiraganaText_Description_PlasmaBeam": 138695476, "sHiraganaText_Description_Missiles": 138695502, "sHiraganaText_Description_SuperMissiles": 138695562, "sHiraganaText_Description_Bombs": 138695656, "sHiraganaText_Description_PowerBombs": 138695688, "sHiraganaText_Description_VariaSuit": 138695758, "sHiraganaText_Description_GravitySuit": 138695866, "sHiraganaText_Description_MorphBall": 138695972, "sHiraganaText_Description_PowerGrip": 138696042, "sHiraganaText_Description_Speedbooster": 138696090, "sHiraganaText_Description_HighJump": 138696206, "sHiraganaText_Description_ScrewAttack": 138696282, "sHiraganaText_Description_SpaceJump": 138696348, "sHiraganaText_Description_UnknownItem": 138696452, "sHiraganaText_Description_Pistol": 138696516, "sHiraganaText_Story_PlanetZebes": 138696620, "sHiraganaText_Story_TheTiming": 138696946, "sHiraganaText_Story_CouldISurvive": 138697336, "sHiraganaText_Story_Emergency": 138697378, "sHiraganaText_Story_Exterminate": 138697398, "sHiraganaText_Story_Defeat": 138697470, "sHiraganaText_FileScreen_StartGame": 138697528, "sHiraganaText_FileScreen_CopySourceChoose": 138697568, "sHiraganaText_FileScreen_CopyDestinationChoose": 138697606, "sHiraganaText_FileScreen_CopyConfirm": 138697660, "sHiraganaText_FileScreen_EraseChoose": 138697740, "sHiraganaText_FileScreen_EraseConfirm": 138697768, "sHiraganaText_FileScreen_FileACorruptRevert": 138697838, "sHiraganaText_FileScreen_FileBCorruptRevert": 138697906, "sHiraganaText_FileScreen_FileCCorruptRevert": 138697974, "sHiraganaText_FileScreen_FileACorruptErase": 138698042, "sHiraganaText_FileScreen_FileBCorruptErase": 138698108, "sHiraganaText_FileScreen_FileCCorruptErase": 138698174, "sHiraganaText_FileScreen_EraseAllReformat": 138698240, "sHiraganaText_FileScreen_EraseAll": 138698306, "sHiraganaText_FileScreen_ContinueNew": 138698368, "sHiraganaText_FileScreen_ContinueNewTimeAttack": 138698392, "sHiraganaText_FileScreen_MessageOption": 138698450, "sHiraganaText_FileScreen_Difficulty": 138698522, "sHiraganaText_FileScreen_DifficultyHard": 138698594, "sHiraganaText_FileScreen_EraseFileConfirm": 138698698, "sHiraganaText_FileScreen_LinkingPleaseWait": 138698816, "sHiraganaText_FileScreen_UnableToDetectFusion": 138698864, "sHiraganaText_FileScreen_LinkingError": 138698930, "sHiraganaText_FileScreen_TurnOffConfirmLink": 138698950, "sHiraganaText_FileScreen_DoNotTurnPowerOff": 138699062, "sHiraganaText_FileScreen_DataUploadComplete": 138699096, "sHiraganaText_FileScreen_LinkComplete": 138699134, "sHiraganaText_FileScreen_BestTime": 138699186, "sHiraganaText_FileScreen_BestTime100": 138699202, "sHiraganaText_FileScreen_IdPassword": 138699226, "sHiraganaText_FileScreen_CantCopyTimeAttack": 138699244, "sHiraganaText_FileScreen_LinkingErrorTryAgain": 138699296, "sHiraganaText_FileScreen_LinkingErrorCheckConnection": 138699340, "sHiraganaText_FileScreen_GalleryUnlock": 138699442, "sHiraganaText_FileScreen_TimeAttackRecordUnlock": 138699524, "sHiraganaText_FileScreen_SoundTestUnlock": 138699618, "sHiraganaText_FileScreen_NesMetroidUnlock": 138699704, "sEnglishText_Description_LongBeam": 138699796, "sEnglishText_Description_ChargeBeam": 138699942, "sEnglishText_Description_IceBeam": 138700092, "sEnglishText_Description_WaveBeam": 138700250, "sEnglishText_Description_PlasmaBeam": 138700404, "sEnglishText_Description_Missiles": 138700514, "sEnglishText_Description_SuperMissiles": 138700598, "sEnglishText_Description_Bombs": 138700706, "sEnglishText_Description_PowerBombs": 138700776, "sEnglishText_Description_VariaSuit": 138700894, "sEnglishText_Description_GravitySuit": 138701040, "sEnglishText_Description_MorphBall": 138701194, "sEnglishText_Description_PowerGrip": 138701334, "sEnglishText_Description_Speedbooster": 138701416, "sEnglishText_Description_HighJump": 138701562, "sEnglishText_Description_ScrewAttack": 138701696, "sEnglishText_Description_SpaceJump": 138701768, "sEnglishText_Description_UnknownItem": 138701910, "sEnglishText_Description_Pistol": 138702034, "sEnglishText_Story_PlanetZebes": 138702164, "sEnglishText_Story_TheTiming": 138702634, "sEnglishText_Story_CouldISurvive": 138703234, "sEnglishText_Story_Emergency": 138703312, "sEnglishText_Story_Exterminate": 138703344, "sEnglishText_Story_Defeat": 138703450, "sEnglishText_FileScreen_StartGame": 138703552, "sEnglishText_FileScreen_CopySourceChoose": 138703610, "sEnglishText_FileScreen_CopyDestinationChoose": 138703666, "sEnglishText_FileScreen_CopyConfirm": 138703736, "sEnglishText_FileScreen_EraseChoose": 138703820, "sEnglishText_FileScreen_EraseConfirm": 138703878, "sEnglishText_FileScreen_FileACorruptRevert": 138703964, "sEnglishText_FileScreen_FileBCorruptRevert": 138704054, "sEnglishText_FileScreen_FileCCorruptRevert": 138704144, "sEnglishText_FileScreen_FileACorruptErase": 138704234, "sEnglishText_FileScreen_FileBCorruptErase": 138704312, "sEnglishText_FileScreen_FileCCorruptErase": 138704390, "sEnglishText_FileScreen_EraseAllReformat": 138704468, "sEnglishText_FileScreen_EraseAll": 138704572, "sEnglishText_FileScreen_ContinueNew": 138704638, "sEnglishText_FileScreen_ContinueNewTimeAttack": 138704664, "sEnglishText_FileScreen_MessageOption": 138704722, "sEnglishText_FileScreen_Difficulty": 138704792, "sEnglishText_FileScreen_DifficultyHard": 138704862, "sEnglishText_FileScreen_EraseFileConfirm": 138704942, "sEnglishText_FileScreen_LinkingPleaseWait": 138705078, "sEnglishText_FileScreen_UnableToDetectFusion": 138705144, "sEnglishText_FileScreen_LinkingError": 138705232, "sEnglishText_FileScreen_TurnOffConfirmLink": 138705262, "sEnglishText_FileScreen_DoNotTurnPowerOff": 138705422, "sEnglishText_FileScreen_DataUploadComplete": 138705476, "sEnglishText_FileScreen_LinkComplete": 138705520, "sEnglishText_FileScreen_BestTime": 138705598, "sEnglishText_FileScreen_BestTime100": 138705620, "sEnglishText_FileScreen_IdPassword": 138705656, "sEnglishText_FileScreen_CantCopyTimeAttack": 138705680, "sEnglishText_FileScreen_LinkingErrorTryAgain": 138705746, "sEnglishText_FileScreen_LinkingErrorCheckConnection": 138705798, "sEnglishText_FileScreen_GalleryUnlock": 138705944, "sEnglishText_FileScreen_TimeAttackRecordUnlock": 138706044, "sEnglishText_FileScreen_SoundTestUnlock": 138706168, "sEnglishText_FileScreen_NesMetroidUnlock": 138706274, "sCommonTilesPal": 140381840, "sDoorTransitionPal": 140381872, "sCommonTilesMotherShipPal": 140382352, "sDoorTransitionMotherShipPal": 140382384, "sHatchFlashingMotherShipPal": 140382864, "sHatchFlashingPal": 140383376, "sProcessProjectileFunctionPointers": 141953536, "sProcessParticleFunctionPointers": 141953600, "sAreaDoorsPointers": 141953844, "sAreaRoomEntryPointers": 141953872, "sAreaScrollPointers": 141954484, "sWaterLoopCounterArray": 141954528, "sNonReformDestroyFunctionPointers": 141954544, "sColorFadingSubroutinePointers": 141954564, "sHazeData": 141954580, "sBackgroundEffectBehaviorPointers": 141954632, "sHatchLockEventsPointers": 141954668, "sDemoRamDataPointers": 141954696, "sTourianEscapeFunctionPointers": 141954760, "sCutsceneScreenShakeOffsets_Set0": 141954768, "sCutsceneScreenShakeOffsetSetPointers": 141954772, "sCutsceneScreenShakeOffsetSetSizes": 141954788, "sJapaneseTextPointers_Message": 141956324, "sJapaneseTextPointers_Location": 141956480, "sHiraganaTextPointers_Message": 141956584, "sHiraganaTextPointers_Location": 141956740, "sEnglishTextPointers_Message": 141956844, "sEnglishTextPointers_Location": 141957000, "sLocationTextPointers": 141957104, "sMessageTextPointers": 141957132, "sFileScreenTextPointers": 141957160, "sJapaneseTextPointers_Description": 141957188, "sJapaneseTextPointers_Story": 141957264, "sJapaneseTextPointers_FileScreen": 141957288, "sHiraganaTextPointers_Description": 141957436, "sHiraganaTextPointers_Story": 141957512, "sHiraganaTextPointers_FileScreen": 141957536, "sEnglishTextPointers_Description": 141957684, "sEnglishTextPointers_Story": 141957760, "sEnglishTextPointers_FileScreen": 141957784, "sRandoSeed": 142571316, "sRandoStartingInventory": 142571456, "sPlacedItems": 142571468, "sRandoLongBeamGfx": 142573664, "sRandoChargeBeamGfx": 142574176, "sRandoUnknownPlasmaBeamGfx": 142574688, "sRandoIceBeamGfx": 142575200, "sRandoWaveBeamGfx": 142575712, "sRandoMorphBallGfx": 142576224, "sRandoBombGfx": 142576736, "sRandoVariaSuitGfx": 142577248, "sRandoUnknownGravitySuitGfx": 142577760, "sRandoSpeedBoosterGfx": 142578272, "sRandoHiJumpGfx": 142578784, "sRandoScrewAttackGfx": 142579296, "sRandoUnknownSpaceJumpGfx": 142579808, "sRandoPowerGripGfx": 142580320, "sRandoEnergyTankSprite": 142580832, "sRandoMissileTankSprite": 142580840, "sRandoSuperMissileTankSprite": 142580848, "sRandoPowerBombTankSprite": 142580856, "sRandoLongBeamSprite": 142580864, "sRandoChargeBeamSprite": 142580872, "sRandoIceBeamSprite": 142580880, "sRandoWaveBeamSprite": 142580888, "sRandoUnknownPlasmaBeamSprite": 142580896, "sRandoBombSprite": 142580904, "sRandoVariaSuitSprite": 142580912, "sRandoUnknownGravitySuitSprite": 142580920, "sRandoMorphBallSprite": 142580928, "sRandoSpeedBoosterSprite": 142580936, "sRandoHiJumpSprite": 142580944, "sRandoScrewAttackSprite": 142580952, "sRandoUnknownSpaceJumpSprite": 142580960, "sRandoPowerGripSprite": 142580968, "sRandoExtraData": 142580976}}